vivarium_inputs/__about__.py
vivarium_inputs/__init__.py
vivarium_inputs/_version.py
vivarium_inputs/core.py
vivarium_inputs/extract.py
vivarium_inputs/globals.py
vivarium_inputs/interface.py
vivarium_inputs/utilities.py
vivarium_inputs/utility_data.py
vivarium_inputs/mapping_extension/__init__.py
vivarium_inputs/mapping_extension/alternative_risk_factor.py
vivarium_inputs/mapping_extension/alternative_risk_factor_template.py
vivarium_inputs/mapping_extension/health_technology.py
vivarium_inputs/mapping_extension/health_technology_template.py
vivarium_inputs/mapping_extension/healthcare_entity.py
vivarium_inputs/mapping_extension/healthcare_entity_template.py
vivarium_inputs/testing/__init__.py
vivarium_inputs/testing/test_load.py
vivarium_inputs/validation/__init__.py
vivarium_inputs/validation/raw.py
vivarium_inputs/validation/shared.py
vivarium_inputs/validation/sim.py
vivarium_inputs-5.2.6.dist-info/AUTHORS.rst
vivarium_inputs-5.2.6.dist-info/LICENSE.txt
vivarium_inputs-5.2.6.dist-info/METADATA
vivarium_inputs-5.2.6.dist-info/WHEEL
vivarium_inputs-5.2.6.dist-info/top_level.txt
vivarium_inputs-5.2.6.dist-info/RECORD
