Metadata-Version: 2.2
Name: vivarium_inputs
Version: 5.2.6
Summary: Transformations and artifact building for the vivarium microsimulation project.
Home-page: https://github.com/ihmeuw/vivarium_inputs
Author: The vivarium developers
Author-email: vivarium.dev@gmail.com
License-File: LICENSE.txt
License-File: AUTHORS.rst
Requires-Dist: numpy<2.0.0
Requires-Dist: scipy
Requires-Dist: pandas
Requires-Dist: click
Requires-Dist: joblib
Requires-Dist: tables
Requires-Dist: vivarium>=1.2.1
Requires-Dist: gbd_mapping<5.0.0,>=4.0.0
Requires-Dist: loguru
Provides-Extra: docs
Requires-Dist: sphinx<8.0,>=7.0; extra == "docs"
Requires-Dist: sphinx-rtd-theme; extra == "docs"
Requires-Dist: sphinx-autodoc-typehints; extra == "docs"
Provides-Extra: test
Requires-Dist: pytest; extra == "test"
Requires-Dist: pytest-cov; extra == "test"
Requires-Dist: pytest-mock; extra == "test"
Requires-Dist: hypothesis; extra == "test"
Provides-Extra: data
Requires-Dist: vivarium-gbd-access<5.0.0,>=4.1.0; extra == "data"
Requires-Dist: core-maths; extra == "data"
Provides-Extra: dev
Requires-Dist: sphinx<8.0,>=7.0; extra == "dev"
Requires-Dist: sphinx-rtd-theme; extra == "dev"
Requires-Dist: sphinx-autodoc-typehints; extra == "dev"
Requires-Dist: pytest; extra == "dev"
Requires-Dist: pytest-cov; extra == "dev"
Requires-Dist: pytest-mock; extra == "dev"
Requires-Dist: hypothesis; extra == "dev"
Requires-Dist: vivarium-gbd-access<5.0.0,>=4.1.0; extra == "dev"
Requires-Dist: core-maths; extra == "dev"
Requires-Dist: black==22.3.0; extra == "dev"
Requires-Dist: isort==5.13.2; extra == "dev"
Dynamic: author
Dynamic: author-email
Dynamic: description
Dynamic: home-page
Dynamic: provides-extra
Dynamic: requires-dist
Dynamic: summary
